sqla_connector/__init__.py
sqla_connector/config.py
sqla_connector/sqla_connectoy.py
sqla_connector-0.0.1.dist-info/LICENSE.txt
sqla_connector-0.0.1.dist-info/METADATA
sqla_connector-0.0.1.dist-info/WHEEL
sqla_connector-0.0.1.dist-info/top_level.txt
sqla_connector-0.0.1.dist-info/RECORD
