Metadata-Version: 2.1
Name: sqla-connector
Version: 0.0.1
Summary: Melhora o acessibilidade ao sqla-connector
Author: Mariano Tupã
Author-email: marianotupa@gmail.com
License: MIT License
Keywords: sqlalchemy database
License-File: LICENSE.txt
Requires-Dist: sqlalchemy
